pweb_auth/__init__.py
pweb_auth/pweb_auth_module.py
pweb_auth/cli/__init__.py
pweb_auth/common/__init__.py
pweb_auth/common/pweb_auth_config.py
pweb_auth/common/pweb_auth_init.py
pweb_auth/common/pweb_auth_interceptor_abc.py
pweb_auth/common/pweb_auth_notify_abc.py
pweb_auth/common/pweb_auth_util.py
pweb_auth/data/__init__.py
pweb_auth/data/pweb_auth_enum.py
pweb_auth/data/pweb_auth_registry.py
pweb_auth/form_dto/__init__.py
pweb_auth/form_dto/pweb_auth_dto.py
pweb_auth/model/__init__.py
pweb_auth/model/operator_abc.py
pweb_auth/model/operator_token_abc.py
pweb_auth/model/pweb_auth_model.py
pweb_auth/security/__init__.py
pweb_auth/security/pweb_auth_interceptor.py
pweb_auth/security/pweb_jwt.py
pweb_auth/security/pweb_pass.py
pweb_auth/security/pweb_rest_util.py
pweb_auth/security/pweb_security_util.py
pweb_auth/security/pweb_session.py
pweb_auth/security/pweb_ssr_auth.py
pweb_auth/service/__init__.py
pweb_auth/service/operator_api_service.py
pweb_auth/service/operator_service.py
pweb_auth/service/operator_ssr_service.py
pweb_auth-0.0.7.dist-info/LICENSE
pweb_auth-0.0.7.dist-info/METADATA
pweb_auth-0.0.7.dist-info/WHEEL
pweb_auth-0.0.7.dist-info/top_level.txt
pweb_auth-0.0.7.dist-info/RECORD
