Metadata-Version: 2.1
Name: pweb-auth
Version: 0.0.7
Summary: PWeb authentication system, which allow to manage application basic level authentication, but it can be extensible
Home-page: https://github.com/banglafighter/pweb-auth
Author: Bangla Fighter
Author-email: banglafighter.com@gmail.com
License: Apache 2.0
Platform: any
Classifier: Intended Audience :: Developers
Classifier: License :: OSI Approved :: Apache Software License
Classifier: Programming Language :: Python
License-File: LICENSE
Requires-Dist: bcrypt ==4.0.1
Requires-Dist: PyJWT ==2.8.0
Requires-Dist: pweb-orm
Requires-Dist: pweb-form-rest
Requires-Dist: ppy-jsonyml
